model_unpickler/__init__.py
model_unpickler/gen_whitelist.py
model_unpickler/pk_whitelist.json
model_unpickler/safe_pickler.py
model_unpickler-0.1.dist-info/LICENSE
model_unpickler-0.1.dist-info/METADATA
model_unpickler-0.1.dist-info/WHEEL
model_unpickler-0.1.dist-info/top_level.txt
model_unpickler-0.1.dist-info/RECORD
